{"name":"build-javascript","namedChunkGroups":{"polyfill":{"name":"polyfill","assets":[{"name":"webpack-runtime-99839a1cc2f5210292b8.js","size":3267},{"name":"polyfill-495cb7e7e84556cd1f6f.js","size":85033}],"filteredAssets":0,"assetsSize":88300,"filteredAuxiliaryAssets":2,"auxiliaryAssetsSize":224254},"app":{"name":"app","assets":[{"name":"webpack-runtime-99839a1cc2f5210292b8.js","size":3267},{"name":"framework-db426f55d0326eec22b8.js","size":140741},{"name":"app-55bbc8507fc532860cd6.js","size":68795}],"filteredAssets":0,"assetsSize":212803,"filteredAuxiliaryAssets":3,"auxiliaryAssetsSize":666201},"component---src-pages-404-tsx":{"name":"component---src-pages-404-tsx","assets":[{"name":"component---src-pages-404-tsx-06661b2b594f715d2985.js","size":414}],"filteredAssets":0,"assetsSize":414,"filteredAuxiliaryAssets":1,"auxiliaryAssetsSize":643},"component---src-pages-index-tsx":{"name":"component---src-pages-index-tsx","assets":[{"name":"d60b5658-dd504d9991e4feb94ad5.js","size":212305},{"name":"component---src-pages-index-tsx-2ecb30fe6dbb5c38f17d.js","size":8408}],"filteredAssets":0,"assetsSize":220713,"filteredAuxiliaryAssets":2,"auxiliaryAssetsSize":566927}},"assetsByChunkName":{"polyfill":["webpack-runtime-99839a1cc2f5210292b8.js","polyfill-495cb7e7e84556cd1f6f.js"],"app":["webpack-runtime-99839a1cc2f5210292b8.js","framework-db426f55d0326eec22b8.js","app-55bbc8507fc532860cd6.js"],"component---src-pages-404-tsx":["component---src-pages-404-tsx-06661b2b594f715d2985.js"],"component---src-pages-index-tsx":["d60b5658-dd504d9991e4feb94ad5.js","component---src-pages-index-tsx-2ecb30fe6dbb5c38f17d.js"]},"childAssetsByChunkName":{}}